[
  {
    "id": "3150002318",
    "track_id": 2,
    "bbox": [
      1865,
      335,
      40,
      93
    ],
    "true_role": "player",
    "true_jersey": "76",
    "true_team": "right",
    "predicted_role": "player",
    "role_confidence": 3.6934471130371094,
    "embedding_shape": [
      1,
      256
    ]
  },
  {
    "id": "3150002319",
    "track_id": 3,
    "bbox": [
      1562,
      293,
      34,
      74
    ],
    "true_role": "player",
    "true_jersey": null,
    "true_team": "right",
    "predicted_role": "player",
    "role_confidence": 1.49405837059021,
    "embedding_shape": [
      1,
      256
    ]
  },
  {
    "id": "3150002320",
    "track_id": 4,
    "bbox": [
      1853,
      511,
      58,
      132
    ],
    "true_role": "player",
    "true_jersey": "45",
    "true_team": "right",
    "predicted_role": "player",
    "role_confidence": 3.6799535751342773,
    "embedding_shape": [
      1,
      256
    ]
  },
  {
    "id": "3150002321",
    "track_id": 6,
    "bbox": [
      1319,
      710,
      88,
      176
    ],
    "true_role": "player",
    "true_jersey": "8",
    "true_team": "left",
    "predicted_role": "player",
    "role_confidence": 3.7187371253967285,
    "embedding_shape": [
      1,
      256
    ]
  },
  {
    "id": "3150002322",
    "track_id": 7,
    "bbox": [
      1612,
      562,
      50,
      139
    ],
    "true_role": "player",
    "true_jersey": "26",
    "true_team": "left",
    "predicted_role": "player",
    "role_confidence": 3.590945243835449,
    "embedding_shape": [
      1,
      256
    ]
  },
  {
    "id": "3150002323",
    "track_id": 8,
    "bbox": [
      1671,
      304,
      33,
      75
    ],
    "true_role": "player",
    "true_jersey": "2",
    "true_team": "left",
    "predicted_role": "player",
    "role_confidence": 3.653925895690918,
    "embedding_shape": [
      1,
      256
    ]
  },
  {
    "id": "3150002325",
    "track_id": 13,
    "bbox": [
      1465,
      375,
      47,
      98
    ],
    "true_role": "player",
    "true_jersey": "56",
    "true_team": "right",
    "predicted_role": "player",
    "role_confidence": 3.6266398429870605,
    "embedding_shape": [
      1,
      256
    ]
  },
  {
    "id": "3150002326",
    "track_id": 14,
    "bbox": [
      1551,
      453,
      78,
      105
    ],
    "true_role": "referee",
    "true_jersey": null,
    "true_team": null,
    "predicted_role": "referee",
    "role_confidence": 5.096978187561035,
    "embedding_shape": [
      1,
      256
    ]
  },
  {
    "id": "3150002327",
    "track_id": 15,
    "bbox": [
      1297,
      588,
      39,
      143
    ],
    "true_role": "player",
    "true_jersey": "4",
    "true_team": "right",
    "predicted_role": "player",
    "role_confidence": 3.5228374004364014,
    "embedding_shape": [
      1,
      256
    ]
  },
  {
    "id": "3150002328",
    "track_id": 16,
    "bbox": [
      1049,
      564,
      78,
      135
    ],
    "true_role": "player",
    "true_jersey": "56",
    "true_team": "left",
    "predicted_role": "player",
    "role_confidence": 3.707890748977661,
    "embedding_shape": [
      1,
      256
    ]
  },
  {
    "id": "3150002329",
    "track_id": 17,
    "bbox": [
      1062,
      412,
      44,
      116
    ],
    "true_role": "player",
    "true_jersey": "12",
    "true_team": "left",
    "predicted_role": "player",
    "role_confidence": 3.6109743118286133,
    "embedding_shape": [
      1,
      256
    ]
  },
  {
    "id": "3150002330",
    "track_id": 18,
    "bbox": [
      795,
      831,
      77,
      184
    ],
    "true_role": "player",
    "true_jersey": "44",
    "true_team": "right",
    "predicted_role": "player",
    "role_confidence": 3.523369789123535,
    "embedding_shape": [
      1,
      256
    ]
  },
  {
    "id": "3150002331",
    "track_id": 19,
    "bbox": [
      915,
      712,
      89,
      159
    ],
    "true_role": "player",
    "true_jersey": "23",
    "true_team": "left",
    "predicted_role": "player",
    "role_confidence": 3.528724431991577,
    "embedding_shape": [
      1,
      256
    ]
  },
  {
    "id": "3150002332",
    "track_id": 20,
    "bbox": [
      709,
      660,
      69,
      185
    ],
    "true_role": "player",
    "true_jersey": "27",
    "true_team": "right",
    "predicted_role": "player",
    "role_confidence": 3.618556499481201,
    "embedding_shape": [
      1,
      256
    ]
  },
  {
    "id": "3150002333",
    "track_id": 21,
    "bbox": [
      563,
      692,
      64,
      184
    ],
    "true_role": "player",
    "true_jersey": "25",
    "true_team": "left",
    "predicted_role": "player",
    "role_confidence": 3.594365358352661,
    "embedding_shape": [
      1,
      256
    ]
  },
  {
    "id": "3150002334",
    "track_id": 22,
    "bbox": [
      625,
      275,
      33,
      72
    ],
    "true_role": "player",
    "true_jersey": null,
    "true_team": "right",
    "predicted_role": "player",
    "role_confidence": 2.4716014862060547,
    "embedding_shape": [
      1,
      256
    ]
  },
  {
    "id": "3150002335",
    "track_id": 23,
    "bbox": [
      421,
      158,
      21,
      40
    ],
    "true_role": "referee",
    "true_jersey": null,
    "true_team": null,
    "predicted_role": "referee",
    "role_confidence": 4.788471221923828,
    "embedding_shape": [
      1,
      256
    ]
  },
  {
    "id": "3150002336",
    "track_id": 24,
    "bbox": [
      342,
      309,
      41,
      81
    ],
    "true_role": "player",
    "true_jersey": "3",
    "true_team": "left",
    "predicted_role": "player",
    "role_confidence": 3.6968295574188232,
    "embedding_shape": [
      1,
      256
    ]
  },
  {
    "id": "3150002337",
    "track_id": 25,
    "bbox": [
      10,
      551,
      51,
      144
    ],
    "true_role": "player",
    "true_jersey": "20",
    "true_team": "left",
    "predicted_role": "player",
    "role_confidence": 3.6884865760803223,
    "embedding_shape": [
      1,
      256
    ]
  }
]