[
  {
    "id": "3189007347",
    "track_id": 1,
    "bbox": [
      1572,
      261,
      53,
      74
    ],
    "true_role": "player",
    "true_jersey": null,
    "true_team": "left",
    "predicted_role": "player",
    "role_confidence": 3.7213361263275146,
    "embedding_shape": [
      1,
      256
    ]
  },
  {
    "id": "3189007348",
    "track_id": 7,
    "bbox": [
      1826,
      479,
      74,
      99
    ],
    "true_role": "player",
    "true_jersey": "34",
    "true_team": "left",
    "predicted_role": "player",
    "role_confidence": 3.482893943786621,
    "embedding_shape": [
      1,
      256
    ]
  },
  {
    "id": "3189007349",
    "track_id": 8,
    "bbox": [
      674,
      576,
      68,
      95
    ],
    "true_role": "player",
    "true_jersey": "16",
    "true_team": "left",
    "predicted_role": "player",
    "role_confidence": 3.7975175380706787,
    "embedding_shape": [
      1,
      256
    ]
  },
  {
    "id": "3189007350",
    "track_id": 11,
    "bbox": [
      726,
      664,
      63,
      113
    ],
    "true_role": "player",
    "true_jersey": "9",
    "true_team": "right",
    "predicted_role": "player",
    "role_confidence": 3.696735382080078,
    "embedding_shape": [
      1,
      256
    ]
  },
  {
    "id": "3189007351",
    "track_id": 13,
    "bbox": [
      1046,
      379,
      50,
      84
    ],
    "true_role": "player",
    "true_jersey": "15",
    "true_team": "right",
    "predicted_role": "player",
    "role_confidence": 3.7136895656585693,
    "embedding_shape": [
      1,
      256
    ]
  },
  {
    "id": "3189007352",
    "track_id": 14,
    "bbox": [
      1598,
      372,
      45,
      80
    ],
    "true_role": "player",
    "true_jersey": "14",
    "true_team": "right",
    "predicted_role": "player",
    "role_confidence": 3.7939140796661377,
    "embedding_shape": [
      1,
      256
    ]
  },
  {
    "id": "3189007353",
    "track_id": 15,
    "bbox": [
      1872,
      412,
      34,
      82
    ],
    "true_role": "player",
    "true_jersey": "10",
    "true_team": "right",
    "predicted_role": "player",
    "role_confidence": 3.686692476272583,
    "embedding_shape": [
      1,
      256
    ]
  },
  {
    "id": "3189007354",
    "track_id": 19,
    "bbox": [
      1678,
      403,
      52,
      81
    ],
    "true_role": "referee",
    "true_jersey": null,
    "true_team": null,
    "predicted_role": "other",
    "role_confidence": 0.6493780016899109,
    "embedding_shape": [
      1,
      256
    ]
  },
  {
    "id": "3189007356",
    "track_id": 21,
    "bbox": [
      1204,
      387,
      59,
      83
    ],
    "true_role": "player",
    "true_jersey": "10",
    "true_team": "left",
    "predicted_role": "player",
    "role_confidence": 3.6871259212493896,
    "embedding_shape": [
      1,
      256
    ]
  },
  {
    "id": "3189007357",
    "track_id": 22,
    "bbox": [
      1203,
      632,
      62,
      99
    ],
    "true_role": "player",
    "true_jersey": "27",
    "true_team": "right",
    "predicted_role": "player",
    "role_confidence": 3.713310956954956,
    "embedding_shape": [
      1,
      256
    ]
  },
  {
    "id": "3189007358",
    "track_id": 23,
    "bbox": [
      919,
      158,
      38,
      58
    ],
    "true_role": "referee",
    "true_jersey": null,
    "true_team": null,
    "predicted_role": "referee",
    "role_confidence": 3.3877906799316406,
    "embedding_shape": [
      1,
      256
    ]
  },
  {
    "id": "3189007359",
    "track_id": 24,
    "bbox": [
      597,
      466,
      64,
      86
    ],
    "true_role": "player",
    "true_jersey": "62",
    "true_team": "left",
    "predicted_role": "player",
    "role_confidence": 3.845961570739746,
    "embedding_shape": [
      1,
      256
    ]
  }
]