[
  {
    "id": "3144009113",
    "track_id": 5,
    "bbox": [
      1752,
      545,
      64,
      156
    ],
    "true_role": "player",
    "true_jersey": "4",
    "true_team": "right",
    "predicted_role": "player",
    "role_confidence": 3.628671169281006,
    "embedding_shape": [
      1,
      256
    ]
  },
  {
    "id": "3144009114",
    "track_id": 6,
    "bbox": [
      1823,
      464,
      63,
      141
    ],
    "true_role": "player",
    "true_jersey": "14",
    "true_team": "right",
    "predicted_role": "player",
    "role_confidence": 3.7053401470184326,
    "embedding_shape": [
      1,
      256
    ]
  },
  {
    "id": "3144009115",
    "track_id": 9,
    "bbox": [
      1321,
      417,
      41,
      121
    ],
    "true_role": "player",
    "true_jersey": "93",
    "true_team": "right",
    "predicted_role": "player",
    "role_confidence": 3.0521318912506104,
    "embedding_shape": [
      1,
      256
    ]
  },
  {
    "id": "3144009116",
    "track_id": 12,
    "bbox": [
      1688,
      601,
      48,
      168
    ],
    "true_role": "player",
    "true_jersey": "7",
    "true_team": "left",
    "predicted_role": "player",
    "role_confidence": 3.7568583488464355,
    "embedding_shape": [
      1,
      256
    ]
  },
  {
    "id": "3144009117",
    "track_id": 13,
    "bbox": [
      0,
      679,
      56,
      192
    ],
    "true_role": "player",
    "true_jersey": "23",
    "true_team": "left",
    "predicted_role": "player",
    "role_confidence": 3.5835797786712646,
    "embedding_shape": [
      1,
      256
    ]
  },
  {
    "id": "3144009118",
    "track_id": 15,
    "bbox": [
      1576,
      500,
      99,
      141
    ],
    "true_role": "referee",
    "true_jersey": null,
    "true_team": null,
    "predicted_role": "referee",
    "role_confidence": 5.090405464172363,
    "embedding_shape": [
      1,
      256
    ]
  },
  {
    "id": "3144009119",
    "track_id": 17,
    "bbox": [
      646,
      558,
      53,
      158
    ],
    "true_role": "player",
    "true_jersey": "10",
    "true_team": "right",
    "predicted_role": "player",
    "role_confidence": 3.7046120166778564,
    "embedding_shape": [
      1,
      256
    ]
  },
  {
    "id": "3144009120",
    "track_id": 18,
    "bbox": [
      1067,
      413,
      40,
      112
    ],
    "true_role": "player",
    "true_jersey": "36",
    "true_team": "left",
    "predicted_role": "player",
    "role_confidence": 3.806652784347534,
    "embedding_shape": [
      1,
      256
    ]
  },
  {
    "id": "3144009121",
    "track_id": 19,
    "bbox": [
      691,
      418,
      50,
      120
    ],
    "true_role": "player",
    "true_jersey": "55",
    "true_team": "left",
    "predicted_role": "player",
    "role_confidence": 3.6199419498443604,
    "embedding_shape": [
      1,
      256
    ]
  },
  {
    "id": "3144009122",
    "track_id": 20,
    "bbox": [
      513,
      453,
      42,
      131
    ],
    "true_role": "player",
    "true_jersey": "11",
    "true_team": "right",
    "predicted_role": "player",
    "role_confidence": 3.6094179153442383,
    "embedding_shape": [
      1,
      256
    ]
  },
  {
    "id": "3144009123",
    "track_id": 21,
    "bbox": [
      197,
      543,
      61,
      160
    ],
    "true_role": "player",
    "true_jersey": "20",
    "true_team": "left",
    "predicted_role": "player",
    "role_confidence": 3.747744560241699,
    "embedding_shape": [
      1,
      256
    ]
  },
  {
    "id": "3144009124",
    "track_id": 22,
    "bbox": [
      321,
      397,
      56,
      121
    ],
    "true_role": "referee",
    "true_jersey": null,
    "true_team": null,
    "predicted_role": "referee",
    "role_confidence": 5.586151599884033,
    "embedding_shape": [
      1,
      256
    ]
  },
  {
    "id": "3144009125",
    "track_id": 23,
    "bbox": [
      160,
      455,
      46,
      144
    ],
    "true_role": "player",
    "true_jersey": "25",
    "true_team": "left",
    "predicted_role": "player",
    "role_confidence": 3.643205404281616,
    "embedding_shape": [
      1,
      256
    ]
  },
  {
    "id": "3144009127",
    "track_id": 25,
    "bbox": [
      1393,
      812,
      71,
      224
    ],
    "true_role": "player",
    "true_jersey": "26",
    "true_team": "left",
    "predicted_role": "player",
    "role_confidence": 3.597914218902588,
    "embedding_shape": [
      1,
      256
    ]
  }
]