[
  {
    "id": "3199005697",
    "track_id": 3,
    "bbox": [
      1314,
      744,
      64,
      121
    ],
    "true_role": "player",
    "true_jersey": "7",
    "true_team": "right",
    "predicted_role": "player",
    "role_confidence": 3.762732744216919,
    "embedding_shape": [
      1,
      256
    ]
  },
  {
    "id": "3199005698",
    "track_id": 4,
    "bbox": [
      1436,
      554,
      68,
      97
    ],
    "true_role": "player",
    "true_jersey": null,
    "true_team": "right",
    "predicted_role": "player",
    "role_confidence": 3.8962345123291016,
    "embedding_shape": [
      1,
      256
    ]
  },
  {
    "id": "3199005699",
    "track_id": 5,
    "bbox": [
      1378,
      524,
      34,
      90
    ],
    "true_role": "goalkeeper",
    "true_jersey": null,
    "true_team": "right",
    "predicted_role": "goalkeeper",
    "role_confidence": 3.2158167362213135,
    "embedding_shape": [
      1,
      256
    ]
  },
  {
    "id": "3199005700",
    "track_id": 6,
    "bbox": [
      1078,
      505,
      45,
      85
    ],
    "true_role": "player",
    "true_jersey": null,
    "true_team": "right",
    "predicted_role": "player",
    "role_confidence": 3.7486791610717773,
    "embedding_shape": [
      1,
      256
    ]
  },
  {
    "id": "3199005701",
    "track_id": 7,
    "bbox": [
      1396,
      616,
      64,
      107
    ],
    "true_role": "player",
    "true_jersey": "30",
    "true_team": "right",
    "predicted_role": "player",
    "role_confidence": 3.781831979751587,
    "embedding_shape": [
      1,
      256
    ]
  },
  {
    "id": "3199005702",
    "track_id": 8,
    "bbox": [
      994,
      530,
      38,
      95
    ],
    "true_role": "player",
    "true_jersey": null,
    "true_team": "right",
    "predicted_role": "player",
    "role_confidence": 3.545548915863037,
    "embedding_shape": [
      1,
      256
    ]
  },
  {
    "id": "3199005703",
    "track_id": 9,
    "bbox": [
      1329,
      572,
      57,
      91
    ],
    "true_role": "player",
    "true_jersey": null,
    "true_team": "right",
    "predicted_role": "player",
    "role_confidence": 3.7875852584838867,
    "embedding_shape": [
      1,
      256
    ]
  },
  {
    "id": "3199005704",
    "track_id": 10,
    "bbox": [
      906,
      509,
      60,
      93
    ],
    "true_role": "player",
    "true_jersey": null,
    "true_team": "right",
    "predicted_role": "player",
    "role_confidence": 3.865111827850342,
    "embedding_shape": [
      1,
      256
    ]
  },
  {
    "id": "3199005705",
    "track_id": 11,
    "bbox": [
      775,
      751,
      73,
      110
    ],
    "true_role": "player",
    "true_jersey": "33",
    "true_team": "right",
    "predicted_role": "player",
    "role_confidence": 3.759389638900757,
    "embedding_shape": [
      1,
      256
    ]
  },
  {
    "id": "3199005706",
    "track_id": 12,
    "bbox": [
      643,
      549,
      57,
      82
    ],
    "true_role": "player",
    "true_jersey": "24",
    "true_team": "right",
    "predicted_role": "player",
    "role_confidence": 3.913245916366577,
    "embedding_shape": [
      1,
      256
    ]
  },
  {
    "id": "3199005707",
    "track_id": 13,
    "bbox": [
      1030,
      585,
      45,
      98
    ],
    "true_role": "player",
    "true_jersey": "62",
    "true_team": "right",
    "predicted_role": "player",
    "role_confidence": 3.798750162124634,
    "embedding_shape": [
      1,
      256
    ]
  },
  {
    "id": "3199005708",
    "track_id": 14,
    "bbox": [
      1336,
      653,
      47,
      106
    ],
    "true_role": "player",
    "true_jersey": null,
    "true_team": "left",
    "predicted_role": "player",
    "role_confidence": 3.7104532718658447,
    "embedding_shape": [
      1,
      256
    ]
  },
  {
    "id": "3199005709",
    "track_id": 15,
    "bbox": [
      593,
      694,
      48,
      107
    ],
    "true_role": "player",
    "true_jersey": "27",
    "true_team": "left",
    "predicted_role": "player",
    "role_confidence": 3.6905758380889893,
    "embedding_shape": [
      1,
      256
    ]
  },
  {
    "id": "3199005710",
    "track_id": 16,
    "bbox": [
      1059,
      545,
      49,
      92
    ],
    "true_role": "player",
    "true_jersey": "14",
    "true_team": "left",
    "predicted_role": "player",
    "role_confidence": 3.8136146068573,
    "embedding_shape": [
      1,
      256
    ]
  },
  {
    "id": "3199005711",
    "track_id": 17,
    "bbox": [
      1013,
      576,
      47,
      95
    ],
    "true_role": "player",
    "true_jersey": "3",
    "true_team": "left",
    "predicted_role": "player",
    "role_confidence": 3.824498414993286,
    "embedding_shape": [
      1,
      256
    ]
  },
  {
    "id": "3199005712",
    "track_id": 18,
    "bbox": [
      1407,
      581,
      52,
      96
    ],
    "true_role": "player",
    "true_jersey": null,
    "true_team": "left",
    "predicted_role": "player",
    "role_confidence": 2.8227059841156006,
    "embedding_shape": [
      1,
      256
    ]
  },
  {
    "id": "3199005713",
    "track_id": 19,
    "bbox": [
      1205,
      538,
      48,
      90
    ],
    "true_role": "player",
    "true_jersey": null,
    "true_team": "left",
    "predicted_role": "player",
    "role_confidence": 3.74928879737854,
    "embedding_shape": [
      1,
      256
    ]
  },
  {
    "id": "3199005714",
    "track_id": 20,
    "bbox": [
      599,
      520,
      64,
      91
    ],
    "true_role": "player",
    "true_jersey": null,
    "true_team": "left",
    "predicted_role": "player",
    "role_confidence": 3.7082278728485107,
    "embedding_shape": [
      1,
      256
    ]
  },
  {
    "id": "3199005715",
    "track_id": 21,
    "bbox": [
      282,
      542,
      41,
      89
    ],
    "true_role": "referee",
    "true_jersey": null,
    "true_team": null,
    "predicted_role": "player",
    "role_confidence": 3.7794620990753174,
    "embedding_shape": [
      1,
      256
    ]
  }
]