[
  {
    "id": "3147005148",
    "track_id": 1,
    "bbox": [
      1081,
      157,
      31,
      84
    ],
    "true_role": "goalkeeper",
    "true_jersey": null,
    "true_team": "left",
    "predicted_role": "goalkeeper",
    "role_confidence": 6.29202938079834,
    "embedding_shape": [
      1,
      256
    ]
  },
  {
    "id": "3147005149",
    "track_id": 3,
    "bbox": [
      568,
      498,
      64,
      173
    ],
    "true_role": "player",
    "true_jersey": "20",
    "true_team": "left",
    "predicted_role": "player",
    "role_confidence": 3.6886303424835205,
    "embedding_shape": [
      1,
      256
    ]
  },
  {
    "id": "3147005150",
    "track_id": 4,
    "bbox": [
      809,
      591,
      78,
      184
    ],
    "true_role": "player",
    "true_jersey": "44",
    "true_team": "right",
    "predicted_role": "player",
    "role_confidence": 3.5626728534698486,
    "embedding_shape": [
      1,
      256
    ]
  },
  {
    "id": "3147005151",
    "track_id": 5,
    "bbox": [
      1216,
      384,
      70,
      154
    ],
    "true_role": "player",
    "true_jersey": null,
    "true_team": "left",
    "predicted_role": "player",
    "role_confidence": 3.5322957038879395,
    "embedding_shape": [
      1,
      256
    ]
  },
  {
    "id": "3147005152",
    "track_id": 6,
    "bbox": [
      1437,
      415,
      72,
      171
    ],
    "true_role": "player",
    "true_jersey": null,
    "true_team": "right",
    "predicted_role": "player",
    "role_confidence": 3.697848081588745,
    "embedding_shape": [
      1,
      256
    ]
  },
  {
    "id": "3147005153",
    "track_id": 11,
    "bbox": [
      1559,
      280,
      43,
      123
    ],
    "true_role": "player",
    "true_jersey": null,
    "true_team": "left",
    "predicted_role": "player",
    "role_confidence": 3.5752346515655518,
    "embedding_shape": [
      1,
      256
    ]
  },
  {
    "id": "3147005154",
    "track_id": 20,
    "bbox": [
      447,
      638,
      75,
      230
    ],
    "true_role": "player",
    "true_jersey": "23",
    "true_team": "left",
    "predicted_role": "player",
    "role_confidence": 3.5682551860809326,
    "embedding_shape": [
      1,
      256
    ]
  }
]