[
  {
    "id": "3199010433",
    "track_id": 1,
    "bbox": [
      1368,
      754,
      57,
      98
    ],
    "true_role": "player",
    "true_jersey": "10",
    "true_team": "left",
    "predicted_role": "player",
    "role_confidence": 3.675039529800415,
    "embedding_shape": [
      1,
      256
    ]
  },
  {
    "id": "3199010435",
    "track_id": 3,
    "bbox": [
      94,
      907,
      98,
      134
    ],
    "true_role": "player",
    "true_jersey": "7",
    "true_team": "right",
    "predicted_role": "player",
    "role_confidence": 3.78519606590271,
    "embedding_shape": [
      1,
      256
    ]
  },
  {
    "id": "3199010436",
    "track_id": 4,
    "bbox": [
      940,
      585,
      50,
      90
    ],
    "true_role": "player",
    "true_jersey": null,
    "true_team": "right",
    "predicted_role": "player",
    "role_confidence": 3.84405517578125,
    "embedding_shape": [
      1,
      256
    ]
  },
  {
    "id": "3199010437",
    "track_id": 5,
    "bbox": [
      1680,
      509,
      53,
      67
    ],
    "true_role": "goalkeeper",
    "true_jersey": null,
    "true_team": "right",
    "predicted_role": "goalkeeper",
    "role_confidence": 3.719059705734253,
    "embedding_shape": [
      1,
      256
    ]
  },
  {
    "id": "3199010438",
    "track_id": 6,
    "bbox": [
      849,
      440,
      37,
      74
    ],
    "true_role": "player",
    "true_jersey": null,
    "true_team": "right",
    "predicted_role": "player",
    "role_confidence": 3.856147050857544,
    "embedding_shape": [
      1,
      256
    ]
  },
  {
    "id": "3199010439",
    "track_id": 7,
    "bbox": [
      1275,
      637,
      46,
      96
    ],
    "true_role": "player",
    "true_jersey": "30",
    "true_team": "right",
    "predicted_role": "player",
    "role_confidence": 3.7779901027679443,
    "embedding_shape": [
      1,
      256
    ]
  },
  {
    "id": "3199010440",
    "track_id": 8,
    "bbox": [
      1038,
      494,
      40,
      81
    ],
    "true_role": "player",
    "true_jersey": null,
    "true_team": "right",
    "predicted_role": "player",
    "role_confidence": 3.7235777378082275,
    "embedding_shape": [
      1,
      256
    ]
  },
  {
    "id": "3199010441",
    "track_id": 9,
    "bbox": [
      992,
      463,
      39,
      79
    ],
    "true_role": "player",
    "true_jersey": null,
    "true_team": "right",
    "predicted_role": "player",
    "role_confidence": 3.728050947189331,
    "embedding_shape": [
      1,
      256
    ]
  },
  {
    "id": "3199010442",
    "track_id": 10,
    "bbox": [
      414,
      507,
      36,
      83
    ],
    "true_role": "player",
    "true_jersey": null,
    "true_team": "right",
    "predicted_role": "player",
    "role_confidence": 3.763643980026245,
    "embedding_shape": [
      1,
      256
    ]
  },
  {
    "id": "3199010443",
    "track_id": 11,
    "bbox": [
      7,
      627,
      68,
      85
    ],
    "true_role": "player",
    "true_jersey": "33",
    "true_team": "right",
    "predicted_role": "player",
    "role_confidence": 3.8846940994262695,
    "embedding_shape": [
      1,
      256
    ]
  },
  {
    "id": "3199010444",
    "track_id": 12,
    "bbox": [
      354,
      450,
      44,
      64
    ],
    "true_role": "player",
    "true_jersey": "24",
    "true_team": "right",
    "predicted_role": "player",
    "role_confidence": 3.860322952270508,
    "embedding_shape": [
      1,
      256
    ]
  },
  {
    "id": "3199010445",
    "track_id": 13,
    "bbox": [
      678,
      372,
      37,
      67
    ],
    "true_role": "player",
    "true_jersey": "62",
    "true_team": "right",
    "predicted_role": "player",
    "role_confidence": 3.7577879428863525,
    "embedding_shape": [
      1,
      256
    ]
  },
  {
    "id": "3199010446",
    "track_id": 14,
    "bbox": [
      733,
      475,
      46,
      80
    ],
    "true_role": "player",
    "true_jersey": null,
    "true_team": "left",
    "predicted_role": "player",
    "role_confidence": 3.681250810623169,
    "embedding_shape": [
      1,
      256
    ]
  },
  {
    "id": "3199010447",
    "track_id": 15,
    "bbox": [
      176,
      836,
      76,
      112
    ],
    "true_role": "player",
    "true_jersey": "27",
    "true_team": "left",
    "predicted_role": "player",
    "role_confidence": 3.797828435897827,
    "embedding_shape": [
      1,
      256
    ]
  },
  {
    "id": "3199010448",
    "track_id": 16,
    "bbox": [
      636,
      476,
      50,
      74
    ],
    "true_role": "player",
    "true_jersey": "14",
    "true_team": "left",
    "predicted_role": "player",
    "role_confidence": 3.7851691246032715,
    "embedding_shape": [
      1,
      256
    ]
  },
  {
    "id": "3199010449",
    "track_id": 17,
    "bbox": [
      630,
      645,
      52,
      98
    ],
    "true_role": "player",
    "true_jersey": "3",
    "true_team": "left",
    "predicted_role": "player",
    "role_confidence": 3.7576849460601807,
    "embedding_shape": [
      1,
      256
    ]
  },
  {
    "id": "3199010450",
    "track_id": 18,
    "bbox": [
      1233,
      526,
      42,
      88
    ],
    "true_role": "player",
    "true_jersey": null,
    "true_team": "left",
    "predicted_role": "player",
    "role_confidence": 3.825214385986328,
    "embedding_shape": [
      1,
      256
    ]
  },
  {
    "id": "3199010451",
    "track_id": 19,
    "bbox": [
      1029,
      458,
      38,
      71
    ],
    "true_role": "player",
    "true_jersey": null,
    "true_team": "left",
    "predicted_role": "player",
    "role_confidence": 3.722583055496216,
    "embedding_shape": [
      1,
      256
    ]
  },
  {
    "id": "3199010452",
    "track_id": 20,
    "bbox": [
      142,
      437,
      57,
      79
    ],
    "true_role": "player",
    "true_jersey": null,
    "true_team": "left",
    "predicted_role": "player",
    "role_confidence": 3.7754132747650146,
    "embedding_shape": [
      1,
      256
    ]
  },
  {
    "id": "3199010453",
    "track_id": 21,
    "bbox": [
      307,
      518,
      39,
      82
    ],
    "true_role": "referee",
    "true_jersey": null,
    "true_team": null,
    "predicted_role": "player",
    "role_confidence": 3.445465087890625,
    "embedding_shape": [
      1,
      256
    ]
  },
  {
    "id": "3199010454",
    "track_id": 23,
    "bbox": [
      59,
      539,
      56,
      83
    ],
    "true_role": "player",
    "true_jersey": null,
    "true_team": "left",
    "predicted_role": "player",
    "role_confidence": 3.8223137855529785,
    "embedding_shape": [
      1,
      256
    ]
  }
]