[
  {
    "id": "3144005290",
    "track_id": 3,
    "bbox": [
      1884,
      473,
      35,
      92
    ],
    "true_role": "player",
    "true_jersey": "33",
    "true_team": "right",
    "predicted_role": "player",
    "role_confidence": 3.6779322624206543,
    "embedding_shape": [
      1,
      256
    ]
  },
  {
    "id": "3144005291",
    "track_id": 4,
    "bbox": [
      1461,
      548,
      74,
      154
    ],
    "true_role": "player",
    "true_jersey": "5",
    "true_team": "right",
    "predicted_role": "player",
    "role_confidence": 3.725818634033203,
    "embedding_shape": [
      1,
      256
    ]
  },
  {
    "id": "3144005292",
    "track_id": 5,
    "bbox": [
      293,
      570,
      78,
      159
    ],
    "true_role": "player",
    "true_jersey": "4",
    "true_team": "right",
    "predicted_role": "player",
    "role_confidence": 3.6021175384521484,
    "embedding_shape": [
      1,
      256
    ]
  },
  {
    "id": "3144005293",
    "track_id": 6,
    "bbox": [
      699,
      467,
      88,
      135
    ],
    "true_role": "player",
    "true_jersey": "14",
    "true_team": "right",
    "predicted_role": "player",
    "role_confidence": 3.76587176322937,
    "embedding_shape": [
      1,
      256
    ]
  },
  {
    "id": "3144005294",
    "track_id": 7,
    "bbox": [
      1289,
      443,
      68,
      134
    ],
    "true_role": "player",
    "true_jersey": "15",
    "true_team": "right",
    "predicted_role": "player",
    "role_confidence": 3.7874369621276855,
    "embedding_shape": [
      1,
      256
    ]
  },
  {
    "id": "3144005295",
    "track_id": 8,
    "bbox": [
      874,
      379,
      55,
      102
    ],
    "true_role": "player",
    "true_jersey": "36",
    "true_team": "right",
    "predicted_role": "player",
    "role_confidence": 3.829193115234375,
    "embedding_shape": [
      1,
      256
    ]
  },
  {
    "id": "3144005296",
    "track_id": 12,
    "bbox": [
      555,
      482,
      68,
      127
    ],
    "true_role": "player",
    "true_jersey": "7",
    "true_team": "left",
    "predicted_role": "player",
    "role_confidence": 3.6174235343933105,
    "embedding_shape": [
      1,
      256
    ]
  },
  {
    "id": "3144005297",
    "track_id": 14,
    "bbox": [
      543,
      416,
      58,
      114
    ],
    "true_role": "player",
    "true_jersey": "10",
    "true_team": "left",
    "predicted_role": "player",
    "role_confidence": 3.7257816791534424,
    "embedding_shape": [
      1,
      256
    ]
  },
  {
    "id": "3144005298",
    "track_id": 15,
    "bbox": [
      612,
      470,
      71,
      122
    ],
    "true_role": "referee",
    "true_jersey": null,
    "true_team": null,
    "predicted_role": "referee",
    "role_confidence": 4.7878007888793945,
    "embedding_shape": [
      1,
      256
    ]
  }
]